petehr/__init__.py
petehr/text2code.py
petehr-0.0.1.dist-info/METADATA
petehr-0.0.1.dist-info/WHEEL
petehr-0.0.1.dist-info/top_level.txt
petehr-0.0.1.dist-info/RECORD
