Metadata-Version: 2.1
Name: petehr
Version: 0.0.1
Summary: Python Toolkit for EHR Processing
Home-page: https://github.com/apvidul/petehr
Author: Vidul Ayakulangara Panickan
Requires-Python: >=3.6
